stated/__init__.py
stated/connection.py
stated/finder.py
stated/graph.py
stated/main.py
stated/peer.py
stated/terminal.py
stated/utils.py
stated-0.1.1a5.dist-info/LICENSE
stated-0.1.1a5.dist-info/METADATA
stated-0.1.1a5.dist-info/entry_points.txt
stated-0.1.1a5.dist-info/WHEEL
stated-0.1.1a5.dist-info/RECORD
